{
  "version": 4,
  "cmakeMinimumRequired": {
    "major": 3,
    "minor": 28
  },
  "configurePresets": [
    {
      "name": "platform_ops-x64-linux",
      "displayName": "PlatformOps Linux x64 (Clang)",
      "inherits": "x64-linux",
      "binaryDir": "${sourceDir}/out/build/${presetName}",
      "cacheVariables": {
        "CMAKE_TOOLCHAIN_FILE": "${sourceDir}/IACrux/cmake/toolchains/x64-linux-clang.cmake"
      }
    },
    {
      "name": "platform_ops-arm64-linux",
      "displayName": "PlatformOps Linux ARM64 (Clang Cross)",
      "inherits": "arm64-linux",
      "binaryDir": "${sourceDir}/out/build/${presetName}",
      "cacheVariables": {
        "CMAKE_TOOLCHAIN_FILE": "${sourceDir}/IACrux/cmake/toolchains/arm64-linux-clang.cmake"
      }
    },
    {
      "name": "platform_ops-x64-windows",
      "displayName": "PlatformOps Windows x64 (Clang)",
      "inherits": "x64-windows",
      "binaryDir": "${sourceDir}/out/build/${presetName}",
      "cacheVariables": {
        "CMAKE_TOOLCHAIN_FILE": "${sourceDir}/IACrux/cmake/toolchains/x64-windows-clang.cmake"
      }
    },
    {
      "name": "platform_ops-arm64-windows",
      "displayName": "PlatformOps Windows ARM64 (Clang Cross)",
      "inherits": "arm64-windows",
      "binaryDir": "${sourceDir}/out/build/${presetName}",
      "cacheVariables": {
        "CMAKE_TOOLCHAIN_FILE": "${sourceDir}/IACrux/cmake/toolchains/arm64-windows-clang.cmake"
      }
    },
    {
      "name": "platform_ops-x64-windows-cross",
      "displayName": "PlatformOps Windows x64 (Clang Cross Linux Host)",
      "inherits": "x64-windows-cross",
      "binaryDir": "${sourceDir}/out/build/${presetName}",
      "cacheVariables": {
        "CMAKE_TOOLCHAIN_FILE": "${sourceDir}/IACrux/cmake/toolchains/x64-windows-cross-clang.cmake"
      }
    }
  ],
  "buildPresets": [
    {
      "name": "platform_ops-x64-linux",
      "configurePreset": "platform_ops-x64-linux"
    },
    {
      "name": "platform_ops-x64-windows",
      "configurePreset": "platform_ops-x64-windows"
    }
  ],
  "testPresets": [
    {
      "name": "platform_ops-x64-linux",
      "configurePreset": "platform_ops-x64-linux",
      "configuration": "Release",
      "output": {
        "outputOnFailure": true
      }
    },
    {
      "name": "platform_ops-x64-windows",
      "configurePreset": "platform_ops-x64-windows",
      "configuration": "Release",
      "output": {
        "outputOnFailure": true
      }
    }
  ],
  "include": [
    "IACrux/CMakePresets.json"
  ]
}